pymake/__init__.py
pymake/__main__.py
pymake/_dist_ver.py
pymake/_main.py
pymake/_pymake.py
pymake/version.py
py_make-0.1.2.dist-info/LICENCE
py_make-0.1.2.dist-info/METADATA
py_make-0.1.2.dist-info/WHEEL
py_make-0.1.2.dist-info/entry_points.txt
py_make-0.1.2.dist-info/top_level.txt
py_make-0.1.2.dist-info/RECORD
